{"Columns":32,"Rows":32,"Cells":[{"Terrain":2,"Triggers":[],"Character":null},{"Terrain":3,"Triggers":[],"Character":null},{"Terrain":3,"Triggers":[],"Character":null},{"Terrain":3,"Triggers":[],"Character":null},{"Terrain":3,"Triggers":[],"Character":null},{"Terrain":3,"Triggers":[],"Character":null},{"Terrain":3,"Triggers":[],"Character":null},{"Terrain":3,"Triggers":[],"Character":null},{"Terrain":3,"Triggers":[],"Character":null},{"Terrain":3,"Triggers":[],"Character":null},{"Terrain":3,"Triggers":[],"Character":null},{"Terrain":3,"Triggers":[],"Character":null},{"Terrain":3,"Triggers":[],"Character":null},{"Terrain":3,"Triggers":[],"Character":null},{"Terrain":2,"Triggers":[],"Character":null},{"Terrain":5,"Triggers":[{"TriggerType":0,"Teleport":{"DestinationMap":"Overworld","DestinationX":10,"DestinationY":9},"Shoppe":null}],"Character":null},{"Terrain":5,"Triggers":[{"TriggerType":0,"Teleport":{"DestinationMap":"Overworld","DestinationX":10,"DestinationY":9},"Shoppe":null}],"Character":null},{"Terrain":2,"Triggers":[],"Character":null},{"Terrain":3,"Triggers":[],"Character":null},{"Terrain":3,"Triggers":[],"Character":null},{"Terrain":3,"Triggers":[],"Character":null},{"Terrain":3,"Triggers":[],"Character":null},{"Terrain":3,"Triggers":[],"Character":null},{"Terrain":3,"Triggers":[],"Character":null},{"Terrain":3,"Triggers":[],"Character":null},{"Terrain":3,"Triggers":[],"Character":null},{"Terrain":3,"Triggers":[],"Character":null},{"Terrain":3,"Triggers":[],"Character":null},{"Terrain":3,"Triggers":[],"Character":null},{"Terrain":3,"Triggers":[],"Character":null},{"Terrain":3,"Triggers":[],"Character":null},{"Terrain":2,"Triggers":[],"Character":null},{"Terrain":4,"Triggers":[],"Character":null},{"Terrain":1,"Triggers":[],"Character":null},{"Terrain":1,"Triggers":[],"Character":null},{"Terrain":1,"Triggers":[],"Character":null},{"Terrain":1,"Triggers":[],"Character":null},{"Terrain":1,"Triggers":[],"Character":null},{"Terrain":1,"Triggers":[],"Character":null},{"Terrain":1,"Triggers":[],"Character":null},{"Terrain":1,"Triggers":[],"Character":null},{"Terrain":1,"Triggers":[],"Character":null},{"Terrain":1,"Triggers":[],"Character":null},{"Terrain":1,"Triggers":[],"Character":null},{"Terrain":1,"Triggers":[],"Character":null},{"Terrain":1,"Triggers":[],"Character":null},{"Terrain":1,"Triggers":[],"Character":null},{"Terrain":5,"Triggers":[],"Character":null},{"Terrain":5,"Triggers":[],"Character":null},{"Terrain":1,"Triggers":[],"Character":null},{"Terrain":1,"Triggers":[],"Character":null},{"Terrain":1,"Triggers":[],"Character":null},{"Terrain":1,"Triggers":[],"Character":null},{"Terrain":1,"Triggers":[],"Character":null},{"Terrain":1,"Triggers":[],"Character":null},{"Terrain":1,"Triggers":[],"Character":null},{"Terrain":1,"Triggers":[],"Character":null},{"Terrain":1,"Triggers":[],"Character":null},{"Terrain":1,"Triggers":[],"Character":null},{"Terrain":1,"Triggers":[],"Character":null},{"Terrain":1,"Triggers":[],"Character":null},{"Terrain":1,"Triggers":[],"Character":null},{"Terrain":1,"Triggers":[],"Character":null},{"Terrain":4,"Triggers":[],"Character":null},{"Terrain":4,"Triggers":[],"Character":null},{"Terrain":1,"Triggers":[],"Character":null},{"Terrain":1,"Triggers":[],"Character":null},{"Terrain":1,"Triggers":[],"Character":null},{"Terrain":1,"Triggers":[],"Character":null},{"Terrain":1,"Triggers":[],"Character":null},{"Terrain":1,"Triggers":[],"Character":null},{"Terrain":1,"Triggers":[],"Character":null},{"Terrain":1,"Triggers":[],"Character":null},{"Terrain":1,"Triggers":[],"Character":null},{"Terrain":1,"Triggers":[],"Character":null},{"Terrain":1,"Triggers":[],"Character":null},{"Terrain":1,"Triggers":[],"Character":null},{"Terrain":1,"Triggers":[],"Character":null},{"Terrain":1,"Triggers":[],"Character":null},{"Terrain":5,"Triggers":[],"Character":null},{"Terrain":5,"Triggers":[],"Character":null},{"Terrain":1,"Triggers":[],"Character":null},{"Terrain":1,"Triggers":[],"Character":null},{"Terrain":1,"Triggers":[],"Character":null},{"Terrain":1,"Triggers":[],"Character":null},{"Terrain":1,"Triggers":[],"Character":null},{"Terrain":1,"Triggers":[],"Character":null},{"Terrain":1,"Triggers":[],"Character":null},{"Terrain":1,"Triggers":[],"Character":null},{"Terrain":1,"Triggers":[],"Character":null},{"Terrain":1,"Triggers":[],"Character":null},{"Terrain":1,"Triggers":[],"Character":null},{"Terrain":1,"Triggers":[],"Character":null},{"Terrain":1,"Triggers":[],"Character":null},{"Terrain":1,"Triggers":[],"Character":null},{"Terrain":4,"Triggers":[],"Character":null},{"Terrain":4,"Triggers":[],"Character":null},{"Terrain":1,"Triggers":[],"Character":null},{"Terrain":1,"Triggers":[],"Character":null},{"Terrain":1,"Triggers":[],"Character":null},{"Terrain":1,"Triggers":[],"Character":null},{"Terrain":1,"Triggers":[],"Character":null},{"Terrain":1,"Triggers":[],"Character":null},{"Terrain":1,"Triggers":[],"Character":null},{"Terrain":1,"Triggers":[],"Character":null},{"Terrain":1,"Triggers":[],"Character":null},{"Terrain":1,"Triggers":[],"Character":null},{"Terrain":1,"Triggers":[],"Character":null},{"Terrain":1,"Triggers":[],"Character":null},{"Terrain":1,"Triggers":[],"Character":null},{"Terrain":1,"Triggers":[],"Character":null},{"Terrain":5,"Triggers":[],"Character":null},{"Terrain":5,"Triggers":[],"Character":null},{"Terrain":1,"Triggers":[],"Character":null},{"Terrain":1,"Triggers":[],"Character":null},{"Terrain":1,"Triggers":[],"Character":null},{"Terrain":1,"Triggers":[],"Character":null},{"Terrain":1,"Triggers":[],"Character":null},{"Terrain":1,"Triggers":[],"Character":null},{"Terrain":1,"Triggers":[],"Character":null},{"Terrain":1,"Triggers":[],"Character":null},{"Terrain":1,"Triggers":[],"Character":null},{"Terrain":1,"Triggers":[],"Character":null},{"Terrain":1,"Triggers":[],"Character":null},{"Terrain":1,"Triggers":[],"Character":null},{"Terrain":1,"Triggers":[],"Character":null},{"Terrain":1,"Triggers":[],"Character":null},{"Terrain":4,"Triggers":[],"Character":null},{"Terrain":4,"Triggers":[],"Character":null},{"Terrain":1,"Triggers":[],"Character":null},{"Terrain":1,"Triggers":[],"Character":null},{"Terrain":1,"Triggers":[],"Character":null},{"Terrain":1,"Triggers":[],"Character":null},{"Terrain":1,"Triggers":[],"Character":null},{"Terrain":1,"Triggers":[],"Character":null},{"Terrain":1,"Triggers":[],"Character":null},{"Terrain":1,"Triggers":[],"Character":null},{"Terrain":1,"Triggers":[],"Character":null},{"Terrain":1,"Triggers":[],"Character":null},{"Terrain":1,"Triggers":[],"Character":null},{"Terrain":1,"Triggers":[],"Character":null},{"Terrain":1,"Triggers":[],"Character":null},{"Terrain":1,"Triggers":[],"Character":null},{"Terrain":5,"Triggers":[],"Character":null},{"Terrain":5,"Triggers":[],"Character":null},{"Terrain":1,"Triggers":[],"Character":null},{"Terrain":1,"Triggers":[],"Character":null},{"Terrain":1,"Triggers":[],"Character":null},{"Terrain":1,"Triggers":[],"Character":null},{"Terrain":1,"Triggers":[],"Character":null},{"Terrain":1,"Triggers":[],"Character":null},{"Terrain":1,"Triggers":[],"Character":null},{"Terrain":1,"Triggers":[],"Character":null},{"Terrain":1,"Triggers":[],"Character":null},{"Terrain":1,"Triggers":[],"Character":null},{"Terrain":1,"Triggers":[],"Character":null},{"Terrain":1,"Triggers":[],"Character":null},{"Terrain":1,"Triggers":[],"Character":null},{"Terrain":1,"Triggers":[],"Character":null},{"Terrain":4,"Triggers":[],"Character":null},{"Terrain":4,"Triggers":[],"Character":null},{"Terrain":1,"Triggers":[],"Character":null},{"Terrain":1,"Triggers":[],"Character":null},{"Terrain":1,"Triggers":[],"Character":null},{"Terrain":1,"Triggers":[],"Character":null},{"Terrain":1,"Triggers":[],"Character":null},{"Terrain":1,"Triggers":[],"Character":null},{"Terrain":1,"Triggers":[],"Character":null},{"Terrain":1,"Triggers":[],"Character":null},{"Terrain":1,"Triggers":[],"Character":null},{"Terrain":1,"Triggers":[],"Character":null},{"Terrain":1,"Triggers":[],"Character":null},{"Terrain":1,"Triggers":[],"Character":null},{"Terrain":1,"Triggers":[],"Character":null},{"Terrain":1,"Triggers":[],"Character":null},{"Terrain":5,"Triggers":[],"Character":null},{"Terrain":5,"Triggers":[],"Character":null},{"Terrain":1,"Triggers":[],"Character":null},{"Terrain":1,"Triggers":[],"Character":null},{"Terrain":1,"Triggers":[],"Character":null},{"Terrain":1,"Triggers":[],"Character":null},{"Terrain":1,"Triggers":[],"Character":null},{"Terrain":1,"Triggers":[],"Character":null},{"Terrain":1,"Triggers":[],"Character":null},{"Terrain":1,"Triggers":[],"Character":null},{"Terrain":1,"Triggers":[],"Character":null},{"Terrain":1,"Triggers":[],"Character":null},{"Terrain":1,"Triggers":[],"Character":null},{"Terrain":1,"Triggers":[],"Character":null},{"Terrain":1,"Triggers":[],"Character":null},{"Terrain":1,"Triggers":[],"Character":null},{"Terrain":4,"Triggers":[],"Character":null},{"Terrain":4,"Triggers":[],"Character":null},{"Terrain":1,"Triggers":[],"Character":null},{"Terrain":1,"Triggers":[],"Character":null},{"Terrain":1,"Triggers":[],"Character":null},{"Terrain":1,"Triggers":[],"Character":null},{"Terrain":1,"Triggers":[],"Character":null},{"Terrain":1,"Triggers":[],"Character":null},{"Terrain":1,"Triggers":[],"Character":null},{"Terrain":1,"Triggers":[],"Character":null},{"Terrain":1,"Triggers":[],"Character":null},{"Terrain":1,"Triggers":[],"Character":null},{"Terrain":1,"Triggers":[],"Character":null},{"Terrain":1,"Triggers":[],"Character":null},{"Terrain":1,"Triggers":[],"Character":null},{"Terrain":1,"Triggers":[],"Character":null},{"Terrain":5,"Triggers":[],"Character":null},{"Terrain":5,"Triggers":[],"Character":null},{"Terrain":1,"Triggers":[],"Character":null},{"Terrain":1,"Triggers":[],"Character":null},{"Terrain":1,"Triggers":[],"Character":null},{"Terrain":1,"Triggers":[],"Character":null},{"Terrain":1,"Triggers":[],"Character":null},{"Terrain":1,"Triggers":[],"Character":null},{"Terrain":1,"Triggers":[],"Character":null},{"Terrain":1,"Triggers":[],"Character":null},{"Terrain":1,"Triggers":[],"Character":null},{"Terrain":1,"Triggers":[],"Character":null},{"Terrain":1,"Triggers":[],"Character":null},{"Terrain":1,"Triggers":[],"Character":null},{"Terrain":1,"Triggers":[],"Character":null},{"Terrain":1,"Triggers":[],"Character":null},{"Terrain":4,"Triggers":[],"Character":null},{"Terrain":4,"Triggers":[],"Character":null},{"Terrain":1,"Triggers":[],"Character":null},{"Terrain":1,"Triggers":[],"Character":null},{"Terrain":1,"Triggers":[],"Character":null},{"Terrain":1,"Triggers":[],"Character":null},{"Terrain":1,"Triggers":[],"Character":null},{"Terrain":1,"Triggers":[],"Character":null},{"Terrain":1,"Triggers":[],"Character":null},{"Terrain":1,"Triggers":[],"Character":null},{"Terrain":1,"Triggers":[],"Character":null},{"Terrain":1,"Triggers":[],"Character":null},{"Terrain":1,"Triggers":[],"Character":null},{"Terrain":1,"Triggers":[],"Character":null},{"Terrain":1,"Triggers":[],"Character":null},{"Terrain":1,"Triggers":[],"Character":null},{"Terrain":5,"Triggers":[],"Character":null},{"Terrain":5,"Triggers":[],"Character":null},{"Terrain":1,"Triggers":[],"Character":null},{"Terrain":1,"Triggers":[],"Character":null},{"Terrain":1,"Triggers":[],"Character":null},{"Terrain":1,"Triggers":[],"Character":null},{"Terrain":1,"Triggers":[],"Character":null},{"Terrain":1,"Triggers":[],"Character":null},{"Terrain":1,"Triggers":[],"Character":null},{"Terrain":1,"Triggers":[],"Character":null},{"Terrain":1,"Triggers":[],"Character":null},{"Terrain":1,"Triggers":[],"Character":null},{"Terrain":1,"Triggers":[],"Character":null},{"Terrain":1,"Triggers":[],"Character":null},{"Terrain":1,"Triggers":[],"Character":null},{"Terrain":1,"Triggers":[],"Character":null},{"Terrain":4,"Triggers":[],"Character":null},{"Terrain":4,"Triggers":[],"Character":null},{"Terrain":1,"Triggers":[],"Character":null},{"Terrain":1,"Triggers":[],"Character":null},{"Terrain":1,"Triggers":[],"Character":null},{"Terrain":1,"Triggers":[],"Character":null},{"Terrain":1,"Triggers":[],"Character":null},{"Terrain":1,"Triggers":[],"Character":null},{"Terrain":1,"Triggers":[],"Character":null},{"Terrain":1,"Triggers":[],"Character":null},{"Terrain":1,"Triggers":[],"Character":null},{"Terrain":1,"Triggers":[],"Character":null},{"Terrain":1,"Triggers":[],"Character":null},{"Terrain":1,"Triggers":[],"Character":null},{"Terrain":1,"Triggers":[],"Character":null},{"Terrain":1,"Triggers":[],"Character":null},{"Terrain":5,"Triggers":[],"Character":null},{"Terrain":5,"Triggers":[],"Character":null},{"Terrain":1,"Triggers":[],"Character":null},{"Terrain":1,"Triggers":[],"Character":null},{"Terrain":1,"Triggers":[],"Character":null},{"Terrain":1,"Triggers":[],"Character":null},{"Terrain":1,"Triggers":[],"Character":null},{"Terrain":1,"Triggers":[],"Character":null},{"Terrain":1,"Triggers":[],"Character":null},{"Terrain":1,"Triggers":[],"Character":null},{"Terrain":1,"Triggers":[],"Character":null},{"Terrain":1,"Triggers":[],"Character":null},{"Terrain":1,"Triggers":[],"Character":null},{"Terrain":1,"Triggers":[],"Character":null},{"Terrain":1,"Triggers":[],"Character":null},{"Terrain":1,"Triggers":[],"Character":null},{"Terrain":4,"Triggers":[],"Character":null},{"Terrain":4,"Triggers":[],"Character":null},{"Terrain":1,"Triggers":[],"Character":null},{"Terrain":1,"Triggers":[],"Character":null},{"Terrain":1,"Triggers":[],"Character":null},{"Terrain":1,"Triggers":[],"Character":null},{"Terrain":1,"Triggers":[],"Character":null},{"Terrain":1,"Triggers":[],"Character":null},{"Terrain":1,"Triggers":[],"Character":null},{"Terrain":1,"Triggers":[],"Character":null},{"Terrain":1,"Triggers":[],"Character":null},{"Terrain":1,"Triggers":[],"Character":null},{"Terrain":1,"Triggers":[],"Character":null},{"Terrain":1,"Triggers":[],"Character":null},{"Terrain":1,"Triggers":[],"Character":null},{"Terrain":1,"Triggers":[],"Character":null},{"Terrain":5,"Triggers":[],"Character":null},{"Terrain":5,"Triggers":[],"Character":null},{"Terrain":1,"Triggers":[],"Character":null},{"Terrain":1,"Triggers":[],"Character":null},{"Terrain":1,"Triggers":[],"Character":null},{"Terrain":1,"Triggers":[],"Character":null},{"Terrain":1,"Triggers":[],"Character":null},{"Terrain":1,"Triggers":[],"Character":null},{"Terrain":1,"Triggers":[],"Character":null},{"Terrain":1,"Triggers":[],"Character":null},{"Terrain":1,"Triggers":[],"Character":null},{"Terrain":1,"Triggers":[],"Character":null},{"Terrain":1,"Triggers":[],"Character":null},{"Terrain":1,"Triggers":[],"Character":null},{"Terrain":1,"Triggers":[],"Character":null},{"Terrain":1,"Triggers":[],"Character":null},{"Terrain":4,"Triggers":[],"Character":null},{"Terrain":4,"Triggers":[],"Character":null},{"Terrain":1,"Triggers":[],"Character":null},{"Terrain":1,"Triggers":[],"Character":null},{"Terrain":1,"Triggers":[],"Character":null},{"Terrain":1,"Triggers":[],"Character":null},{"Terrain":1,"Triggers":[],"Character":null},{"Terrain":1,"Triggers":[],"Character":null},{"Terrain":1,"Triggers":[],"Character":null},{"Terrain":1,"Triggers":[],"Character":null},{"Terrain":1,"Triggers":[],"Character":null},{"Terrain":1,"Triggers":[],"Character":null},{"Terrain":1,"Triggers":[],"Character":null},{"Terrain":1,"Triggers":[],"Character":null},{"Terrain":1,"Triggers":[],"Character":null},{"Terrain":1,"Triggers":[],"Character":null},{"Terrain":5,"Triggers":[],"Character":null},{"Terrain":5,"Triggers":[],"Character":null},{"Terrain":1,"Triggers":[],"Character":null},{"Terrain":1,"Triggers":[],"Character":null},{"Terrain":1,"Triggers":[],"Character":null},{"Terrain":1,"Triggers":[],"Character":null},{"Terrain":1,"Triggers":[],"Character":null},{"Terrain":1,"Triggers":[],"Character":null},{"Terrain":1,"Triggers":[],"Character":null},{"Terrain":1,"Triggers":[],"Character":null},{"Terrain":1,"Triggers":[],"Character":null},{"Terrain":1,"Triggers":[],"Character":null},{"Terrain":1,"Triggers":[],"Character":null},{"Terrain":1,"Triggers":[],"Character":null},{"Terrain":1,"Triggers":[],"Character":null},{"Terrain":1,"Triggers":[],"Character":null},{"Terrain":4,"Triggers":[],"Character":null},{"Terrain":4,"Triggers":[],"Character":null},{"Terrain":1,"Triggers":[],"Character":null},{"Terrain":1,"Triggers":[],"Character":null},{"Terrain":1,"Triggers":[],"Character":null},{"Terrain":1,"Triggers":[],"Character":null},{"Terrain":1,"Triggers":[],"Character":null},{"Terrain":1,"Triggers":[],"Character":null},{"Terrain":1,"Triggers":[],"Character":null},{"Terrain":1,"Triggers":[],"Character":null},{"Terrain":1,"Triggers":[],"Character":null},{"Terrain":1,"Triggers":[],"Character":null},{"Terrain":1,"Triggers":[],"Character":null},{"Terrain":1,"Triggers":[],"Character":null},{"Terrain":1,"Triggers":[],"Character":null},{"Terrain":1,"Triggers":[],"Character":null},{"Terrain":5,"Triggers":[],"Character":null},{"Terrain":5,"Triggers":[],"Character":null},{"Terrain":1,"Triggers":[],"Character":null},{"Terrain":1,"Triggers":[],"Character":null},{"Terrain":1,"Triggers":[],"Character":null},{"Terrain":1,"Triggers":[],"Character":null},{"Terrain":1,"Triggers":[],"Character":null},{"Terrain":1,"Triggers":[],"Character":null},{"Terrain":1,"Triggers":[],"Character":null},{"Terrain":1,"Triggers":[],"Character":null},{"Terrain":1,"Triggers":[],"Character":null},{"Terrain":1,"Triggers":[],"Character":null},{"Terrain":1,"Triggers":[],"Character":null},{"Terrain":1,"Triggers":[],"Character":null},{"Terrain":1,"Triggers":[],"Character":null},{"Terrain":1,"Triggers":[],"Character":null},{"Terrain":4,"Triggers":[],"Character":null},{"Terrain":4,"Triggers":[],"Character":null},{"Terrain":1,"Triggers":[],"Character":null},{"Terrain":1,"Triggers":[],"Character":null},{"Terrain":1,"Triggers":[],"Character":null},{"Terrain":1,"Triggers":[],"Character":null},{"Terrain":1,"Triggers":[],"Character":null},{"Terrain":1,"Triggers":[],"Character":null},{"Terrain":1,"Triggers":[],"Character":null},{"Terrain":1,"Triggers":[],"Character":null},{"Terrain":1,"Triggers":[],"Character":null},{"Terrain":1,"Triggers":[],"Character":null},{"Terrain":1,"Triggers":[],"Character":null},{"Terrain":1,"Triggers":[],"Character":null},{"Terrain":1,"Triggers":[],"Character":null},{"Terrain":1,"Triggers":[],"Character":null},{"Terrain":5,"Triggers":[],"Character":null},{"Terrain":5,"Triggers":[],"Character":null},{"Terrain":1,"Triggers":[],"Character":null},{"Terrain":1,"Triggers":[],"Character":null},{"Terrain":1,"Triggers":[],"Character":null},{"Terrain":1,"Triggers":[],"Character":null},{"Terrain":1,"Triggers":[],"Character":null},{"Terrain":1,"Triggers":[],"Character":null},{"Terrain":1,"Triggers":[],"Character":null},{"Terrain":1,"Triggers":[],"Character":null},{"Terrain":1,"Triggers":[],"Character":null},{"Terrain":1,"Triggers":[],"Character":null},{"Terrain":1,"Triggers":[],"Character":null},{"Terrain":1,"Triggers":[],"Character":null},{"Terrain":1,"Triggers":[],"Character":null},{"Terrain":1,"Triggers":[],"Character":null},{"Terrain":4,"Triggers":[],"Character":null},{"Terrain":4,"Triggers":[],"Character":null},{"Terrain":1,"Triggers":[],"Character":null},{"Terrain":1,"Triggers":[],"Character":null},{"Terrain":1,"Triggers":[],"Character":null},{"Terrain":1,"Triggers":[],"Character":null},{"Terrain":1,"Triggers":[],"Character":null},{"Terrain":1,"Triggers":[],"Character":null},{"Terrain":1,"Triggers":[],"Character":null},{"Terrain":1,"Triggers":[],"Character":null},{"Terrain":1,"Triggers":[],"Character":null},{"Terrain":1,"Triggers":[],"Character":null},{"Terrain":1,"Triggers":[],"Character":null},{"Terrain":1,"Triggers":[],"Character":null},{"Terrain":1,"Triggers":[],"Character":null},{"Terrain":1,"Triggers":[],"Character":null},{"Terrain":5,"Triggers":[],"Character":null},{"Terrain":5,"Triggers":[],"Character":null},{"Terrain":1,"Triggers":[],"Character":null},{"Terrain":1,"Triggers":[],"Character":null},{"Terrain":1,"Triggers":[],"Character":null},{"Terrain":1,"Triggers":[],"Character":null},{"Terrain":1,"Triggers":[],"Character":null},{"Terrain":1,"Triggers":[],"Character":null},{"Terrain":1,"Triggers":[],"Character":null},{"Terrain":1,"Triggers":[],"Character":null},{"Terrain":1,"Triggers":[],"Character":null},{"Terrain":1,"Triggers":[],"Character":null},{"Terrain":1,"Triggers":[],"Character":null},{"Terrain":1,"Triggers":[],"Character":null},{"Terrain":1,"Triggers":[],"Character":null},{"Terrain":1,"Triggers":[],"Character":null},{"Terrain":4,"Triggers":[],"Character":null},{"Terrain":2,"Triggers":[],"Character":null},{"Terrain":1,"Triggers":[],"Character":null},{"Terrain":1,"Triggers":[],"Character":null},{"Terrain":1,"Triggers":[],"Character":null},{"Terrain":1,"Triggers":[],"Character":null},{"Terrain":1,"Triggers":[],"Character":null},{"Terrain":1,"Triggers":[],"Character":null},{"Terrain":1,"Triggers":[],"Character":null},{"Terrain":1,"Triggers":[],"Character":null},{"Terrain":1,"Triggers":[],"Character":null},{"Terrain":1,"Triggers":[],"Character":null},{"Terrain":1,"Triggers":[],"Character":null},{"Terrain":1,"Triggers":[],"Character":null},{"Terrain":1,"Triggers":[],"Character":null},{"Terrain":1,"Triggers":[],"Character":null},{"Terrain":5,"Triggers":[],"Character":null},{"Terrain":5,"Triggers":[],"Character":null},{"Terrain":1,"Triggers":[],"Character":null},{"Terrain":1,"Triggers":[],"Character":null},{"Terrain":1,"Triggers":[],"Character":null},{"Terrain":1,"Triggers":[],"Character":null},{"Terrain":1,"Triggers":[],"Character":null},{"Terrain":1,"Triggers":[],"Character":null},{"Terrain":1,"Triggers":[],"Character":null},{"Terrain":1,"Triggers":[],"Character":null},{"Terrain":1,"Triggers":[],"Character":null},{"Terrain":1,"Triggers":[],"Character":null},{"Terrain":1,"Triggers":[],"Character":null},{"Terrain":1,"Triggers":[],"Character":null},{"Terrain":1,"Triggers":[],"Character":null},{"Terrain":1,"Triggers":[],"Character":null},{"Terrain":2,"Triggers":[],"Character":null},{"Terrain":5,"Triggers":[{"TriggerType":0,"Teleport":{"DestinationMap":"Overworld","DestinationX":9,"DestinationY":10},"Shoppe":null}],"Character":null},{"Terrain":5,"Triggers":[],"Character":null},{"Terrain":5,"Triggers":[],"Character":null},{"Terrain":5,"Triggers":[],"Character":null},{"Terrain":5,"Triggers":[],"Character":null},{"Terrain":5,"Triggers":[],"Character":null},{"Terrain":5,"Triggers":[],"Character":null},{"Terrain":5,"Triggers":[],"Character":null},{"Terrain":5,"Triggers":[],"Character":null},{"Terrain":5,"Triggers":[],"Character":null},{"Terrain":5,"Triggers":[],"Character":null},{"Terrain":5,"Triggers":[],"Character":null},{"Terrain":5,"Triggers":[],"Character":null},{"Terrain":5,"Triggers":[],"Character":null},{"Terrain":5,"Triggers":[],"Character":null},{"Terrain":5,"Triggers":[],"Character":null},{"Terrain":5,"Triggers":[],"Character":null},{"Terrain":5,"Triggers":[],"Character":null},{"Terrain":5,"Triggers":[],"Character":null},{"Terrain":5,"Triggers":[],"Character":null},{"Terrain":5,"Triggers":[],"Character":null},{"Terrain":5,"Triggers":[],"Character":null},{"Terrain":5,"Triggers":[],"Character":null},{"Terrain":5,"Triggers":[],"Character":null},{"Terrain":5,"Triggers":[],"Character":null},{"Terrain":5,"Triggers":[],"Character":null},{"Terrain":5,"Triggers":[],"Character":null},{"Terrain":5,"Triggers":[],"Character":null},{"Terrain":5,"Triggers":[],"Character":null},{"Terrain":5,"Triggers":[],"Character":null},{"Terrain":5,"Triggers":[],"Character":null},{"Terrain":5,"Triggers":[{"TriggerType":0,"Teleport":{"DestinationMap":"Overworld","DestinationX":11,"DestinationY":10},"Shoppe":null}],"Character":null},{"Terrain":5,"Triggers":[{"TriggerType":0,"Teleport":{"DestinationMap":"Overworld","DestinationX":9,"DestinationY":10},"Shoppe":null}],"Character":null},{"Terrain":5,"Triggers":[],"Character":null},{"Terrain":5,"Triggers":[],"Character":null},{"Terrain":5,"Triggers":[],"Character":null},{"Terrain":5,"Triggers":[],"Character":null},{"Terrain":5,"Triggers":[],"Character":null},{"Terrain":5,"Triggers":[],"Character":null},{"Terrain":5,"Triggers":[],"Character":null},{"Terrain":5,"Triggers":[],"Character":null},{"Terrain":5,"Triggers":[],"Character":null},{"Terrain":5,"Triggers":[],"Character":null},{"Terrain":5,"Triggers":[],"Character":null},{"Terrain":5,"Triggers":[],"Character":null},{"Terrain":5,"Triggers":[],"Character":null},{"Terrain":5,"Triggers":[],"Character":null},{"Terrain":5,"Triggers":[],"Character":null},{"Terrain":5,"Triggers":[],"Character":null},{"Terrain":5,"Triggers":[],"Character":null},{"Terrain":5,"Triggers":[],"Character":null},{"Terrain":5,"Triggers":[],"Character":null},{"Terrain":5,"Triggers":[],"Character":null},{"Terrain":5,"Triggers":[],"Character":null},{"Terrain":5,"Triggers":[],"Character":null},{"Terrain":5,"Triggers":[],"Character":null},{"Terrain":5,"Triggers":[],"Character":null},{"Terrain":5,"Triggers":[],"Character":null},{"Terrain":5,"Triggers":[],"Character":null},{"Terrain":5,"Triggers":[],"Character":null},{"Terrain":5,"Triggers":[],"Character":null},{"Terrain":5,"Triggers":[],"Character":null},{"Terrain":5,"Triggers":[],"Character":null},{"Terrain":5,"Triggers":[{"TriggerType":0,"Teleport":{"DestinationMap":"Overworld","DestinationX":11,"DestinationY":10},"Shoppe":null}],"Character":null},{"Terrain":2,"Triggers":[],"Character":null},{"Terrain":1,"Triggers":[],"Character":null},{"Terrain":1,"Triggers":[],"Character":null},{"Terrain":1,"Triggers":[],"Character":null},{"Terrain":1,"Triggers":[],"Character":null},{"Terrain":1,"Triggers":[],"Character":null},{"Terrain":1,"Triggers":[],"Character":null},{"Terrain":1,"Triggers":[],"Character":null},{"Terrain":1,"Triggers":[],"Character":null},{"Terrain":1,"Triggers":[],"Character":null},{"Terrain":1,"Triggers":[],"Character":null},{"Terrain":1,"Triggers":[],"Character":null},{"Terrain":1,"Triggers":[],"Character":null},{"Terrain":1,"Triggers":[],"Character":null},{"Terrain":1,"Triggers":[],"Character":null},{"Terrain":5,"Triggers":[],"Character":null},{"Terrain":5,"Triggers":[],"Character":null},{"Terrain":1,"Triggers":[],"Character":null},{"Terrain":1,"Triggers":[],"Character":null},{"Terrain":1,"Triggers":[],"Character":null},{"Terrain":1,"Triggers":[],"Character":null},{"Terrain":1,"Triggers":[],"Character":null},{"Terrain":1,"Triggers":[],"Character":null},{"Terrain":1,"Triggers":[],"Character":null},{"Terrain":1,"Triggers":[],"Character":null},{"Terrain":1,"Triggers":[],"Character":null},{"Terrain":1,"Triggers":[],"Character":null},{"Terrain":1,"Triggers":[],"Character":null},{"Terrain":1,"Triggers":[],"Character":null},{"Terrain":1,"Triggers":[],"Character":null},{"Terrain":1,"Triggers":[],"Character":null},{"Terrain":2,"Triggers":[],"Character":null},{"Terrain":4,"Triggers":[],"Character":null},{"Terrain":1,"Triggers":[],"Character":null},{"Terrain":1,"Triggers":[],"Character":null},{"Terrain":1,"Triggers":[],"Character":null},{"Terrain":1,"Triggers":[],"Character":null},{"Terrain":1,"Triggers":[],"Character":null},{"Terrain":1,"Triggers":[],"Character":null},{"Terrain":1,"Triggers":[],"Character":null},{"Terrain":1,"Triggers":[],"Character":null},{"Terrain":1,"Triggers":[],"Character":null},{"Terrain":1,"Triggers":[],"Character":null},{"Terrain":1,"Triggers":[],"Character":null},{"Terrain":1,"Triggers":[],"Character":null},{"Terrain":1,"Triggers":[],"Character":null},{"Terrain":1,"Triggers":[],"Character":null},{"Terrain":5,"Triggers":[],"Character":null},{"Terrain":5,"Triggers":[],"Character":null},{"Terrain":1,"Triggers":[],"Character":null},{"Terrain":9,"Triggers":[],"Character":null},{"Terrain":9,"Triggers":[],"Character":null},{"Terrain":9,"Triggers":[],"Character":null},{"Terrain":1,"Triggers":[],"Character":null},{"Terrain":1,"Triggers":[],"Character":null},{"Terrain":1,"Triggers":[],"Character":null},{"Terrain":1,"Triggers":[],"Character":null},{"Terrain":1,"Triggers":[],"Character":null},{"Terrain":1,"Triggers":[],"Character":null},{"Terrain":1,"Triggers":[],"Character":null},{"Terrain":1,"Triggers":[],"Character":null},{"Terrain":1,"Triggers":[],"Character":null},{"Terrain":1,"Triggers":[],"Character":null},{"Terrain":4,"Triggers":[],"Character":null},{"Terrain":4,"Triggers":[],"Character":null},{"Terrain":1,"Triggers":[],"Character":null},{"Terrain":1,"Triggers":[],"Character":null},{"Terrain":1,"Triggers":[],"Character":null},{"Terrain":1,"Triggers":[],"Character":null},{"Terrain":1,"Triggers":[],"Character":null},{"Terrain":1,"Triggers":[],"Character":null},{"Terrain":1,"Triggers":[],"Character":null},{"Terrain":1,"Triggers":[],"Character":null},{"Terrain":1,"Triggers":[],"Character":null},{"Terrain":1,"Triggers":[],"Character":null},{"Terrain":1,"Triggers":[],"Character":null},{"Terrain":1,"Triggers":[],"Character":null},{"Terrain":1,"Triggers":[],"Character":null},{"Terrain":1,"Triggers":[],"Character":null},{"Terrain":5,"Triggers":[],"Character":null},{"Terrain":5,"Triggers":[],"Character":null},{"Terrain":1,"Triggers":[],"Character":null},{"Terrain":9,"Triggers":[],"Character":null},{"Terrain":8,"Triggers":[{"TriggerType":1,"Teleport":null,"Shoppe":{"Prices":{"Club":0.2},"Offers":{"Club":0.1},"Name":"Samuli\u0027s Blacksmithery"}}],"Character":null},{"Terrain":9,"Triggers":[],"Character":null},{"Terrain":1,"Triggers":[],"Character":null},{"Terrain":1,"Triggers":[],"Character":null},{"Terrain":1,"Triggers":[],"Character":null},{"Terrain":1,"Triggers":[],"Character":null},{"Terrain":1,"Triggers":[],"Character":null},{"Terrain":1,"Triggers":[],"Character":null},{"Terrain":1,"Triggers":[],"Character":null},{"Terrain":1,"Triggers":[],"Character":null},{"Terrain":1,"Triggers":[],"Character":null},{"Terrain":1,"Triggers":[],"Character":null},{"Terrain":4,"Triggers":[],"Character":null},{"Terrain":4,"Triggers":[],"Character":null},{"Terrain":1,"Triggers":[],"Character":null},{"Terrain":1,"Triggers":[],"Character":null},{"Terrain":1,"Triggers":[],"Character":null},{"Terrain":1,"Triggers":[],"Character":null},{"Terrain":1,"Triggers":[],"Character":null},{"Terrain":1,"Triggers":[],"Character":null},{"Terrain":1,"Triggers":[],"Character":null},{"Terrain":1,"Triggers":[],"Character":null},{"Terrain":1,"Triggers":[],"Character":null},{"Terrain":1,"Triggers":[],"Character":null},{"Terrain":1,"Triggers":[],"Character":null},{"Terrain":1,"Triggers":[],"Character":null},{"Terrain":1,"Triggers":[],"Character":null},{"Terrain":1,"Triggers":[],"Character":null},{"Terrain":5,"Triggers":[],"Character":null},{"Terrain":5,"Triggers":[],"Character":null},{"Terrain":1,"Triggers":[],"Character":null},{"Terrain":1,"Triggers":[],"Character":null},{"Terrain":5,"Triggers":[],"Character":null},{"Terrain":1,"Triggers":[],"Character":null},{"Terrain":1,"Triggers":[],"Character":null},{"Terrain":1,"Triggers":[],"Character":null},{"Terrain":1,"Triggers":[],"Character":null},{"Terrain":1,"Triggers":[],"Character":null},{"Terrain":1,"Triggers":[],"Character":null},{"Terrain":1,"Triggers":[],"Character":null},{"Terrain":1,"Triggers":[],"Character":null},{"Terrain":1,"Triggers":[],"Character":null},{"Terrain":1,"Triggers":[],"Character":null},{"Terrain":1,"Triggers":[],"Character":null},{"Terrain":4,"Triggers":[],"Character":null},{"Terrain":4,"Triggers":[],"Character":null},{"Terrain":1,"Triggers":[],"Character":null},{"Terrain":1,"Triggers":[],"Character":null},{"Terrain":1,"Triggers":[],"Character":null},{"Terrain":1,"Triggers":[],"Character":null},{"Terrain":1,"Triggers":[],"Character":null},{"Terrain":1,"Triggers":[],"Character":null},{"Terrain":1,"Triggers":[],"Character":null},{"Terrain":1,"Triggers":[],"Character":null},{"Terrain":1,"Triggers":[],"Character":null},{"Terrain":1,"Triggers":[],"Character":null},{"Terrain":1,"Triggers":[],"Character":null},{"Terrain":1,"Triggers":[],"Character":null},{"Terrain":1,"Triggers":[],"Character":null},{"Terrain":1,"Triggers":[],"Character":null},{"Terrain":5,"Triggers":[],"Character":null},{"Terrain":5,"Triggers":[],"Character":null},{"Terrain":5,"Triggers":[],"Character":null},{"Terrain":5,"Triggers":[],"Character":null},{"Terrain":5,"Triggers":[],"Character":null},{"Terrain":1,"Triggers":[],"Character":null},{"Terrain":1,"Triggers":[],"Character":null},{"Terrain":1,"Triggers":[],"Character":null},{"Terrain":1,"Triggers":[],"Character":null},{"Terrain":1,"Triggers":[],"Character":null},{"Terrain":1,"Triggers":[],"Character":null},{"Terrain":1,"Triggers":[],"Character":null},{"Terrain":1,"Triggers":[],"Character":null},{"Terrain":1,"Triggers":[],"Character":null},{"Terrain":1,"Triggers":[],"Character":null},{"Terrain":1,"Triggers":[],"Character":null},{"Terrain":4,"Triggers":[],"Character":null},{"Terrain":4,"Triggers":[],"Character":null},{"Terrain":1,"Triggers":[],"Character":null},{"Terrain":1,"Triggers":[],"Character":null},{"Terrain":1,"Triggers":[],"Character":null},{"Terrain":1,"Triggers":[],"Character":null},{"Terrain":1,"Triggers":[],"Character":null},{"Terrain":1,"Triggers":[],"Character":null},{"Terrain":1,"Triggers":[],"Character":null},{"Terrain":1,"Triggers":[],"Character":null},{"Terrain":1,"Triggers":[],"Character":null},{"Terrain":1,"Triggers":[],"Character":null},{"Terrain":1,"Triggers":[],"Character":null},{"Terrain":1,"Triggers":[],"Character":null},{"Terrain":1,"Triggers":[],"Character":null},{"Terrain":1,"Triggers":[],"Character":null},{"Terrain":5,"Triggers":[],"Character":null},{"Terrain":5,"Triggers":[],"Character":null},{"Terrain":1,"Triggers":[],"Character":null},{"Terrain":1,"Triggers":[],"Character":null},{"Terrain":1,"Triggers":[],"Character":null},{"Terrain":1,"Triggers":[],"Character":null},{"Terrain":1,"Triggers":[],"Character":null},{"Terrain":1,"Triggers":[],"Character":null},{"Terrain":1,"Triggers":[],"Character":null},{"Terrain":1,"Triggers":[],"Character":null},{"Terrain":1,"Triggers":[],"Character":null},{"Terrain":1,"Triggers":[],"Character":null},{"Terrain":1,"Triggers":[],"Character":null},{"Terrain":1,"Triggers":[],"Character":null},{"Terrain":1,"Triggers":[],"Character":null},{"Terrain":1,"Triggers":[],"Character":null},{"Terrain":4,"Triggers":[],"Character":null},{"Terrain":4,"Triggers":[],"Character":null},{"Terrain":1,"Triggers":[],"Character":null},{"Terrain":1,"Triggers":[],"Character":null},{"Terrain":1,"Triggers":[],"Character":null},{"Terrain":1,"Triggers":[],"Character":null},{"Terrain":1,"Triggers":[],"Character":null},{"Terrain":1,"Triggers":[],"Character":null},{"Terrain":1,"Triggers":[],"Character":null},{"Terrain":1,"Triggers":[],"Character":null},{"Terrain":1,"Triggers":[],"Character":null},{"Terrain":1,"Triggers":[],"Character":null},{"Terrain":1,"Triggers":[],"Character":null},{"Terrain":1,"Triggers":[],"Character":null},{"Terrain":1,"Triggers":[],"Character":null},{"Terrain":1,"Triggers":[],"Character":null},{"Terrain":5,"Triggers":[],"Character":null},{"Terrain":5,"Triggers":[],"Character":null},{"Terrain":1,"Triggers":[],"Character":null},{"Terrain":1,"Triggers":[],"Character":null},{"Terrain":1,"Triggers":[],"Character":null},{"Terrain":1,"Triggers":[],"Character":null},{"Terrain":1,"Triggers":[],"Character":null},{"Terrain":1,"Triggers":[],"Character":null},{"Terrain":1,"Triggers":[],"Character":null},{"Terrain":1,"Triggers":[],"Character":null},{"Terrain":1,"Triggers":[],"Character":null},{"Terrain":1,"Triggers":[],"Character":null},{"Terrain":1,"Triggers":[],"Character":null},{"Terrain":1,"Triggers":[],"Character":null},{"Terrain":1,"Triggers":[],"Character":null},{"Terrain":1,"Triggers":[],"Character":null},{"Terrain":4,"Triggers":[],"Character":null},{"Terrain":4,"Triggers":[],"Character":null},{"Terrain":1,"Triggers":[],"Character":null},{"Terrain":1,"Triggers":[],"Character":null},{"Terrain":1,"Triggers":[],"Character":null},{"Terrain":1,"Triggers":[],"Character":null},{"Terrain":1,"Triggers":[],"Character":null},{"Terrain":1,"Triggers":[],"Character":null},{"Terrain":1,"Triggers":[],"Character":null},{"Terrain":1,"Triggers":[],"Character":null},{"Terrain":1,"Triggers":[],"Character":null},{"Terrain":1,"Triggers":[],"Character":null},{"Terrain":1,"Triggers":[],"Character":null},{"Terrain":1,"Triggers":[],"Character":null},{"Terrain":1,"Triggers":[],"Character":null},{"Terrain":1,"Triggers":[],"Character":null},{"Terrain":5,"Triggers":[],"Character":null},{"Terrain":5,"Triggers":[],"Character":null},{"Terrain":1,"Triggers":[],"Character":null},{"Terrain":1,"Triggers":[],"Character":null},{"Terrain":1,"Triggers":[],"Character":null},{"Terrain":1,"Triggers":[],"Character":null},{"Terrain":1,"Triggers":[],"Character":null},{"Terrain":1,"Triggers":[],"Character":null},{"Terrain":1,"Triggers":[],"Character":null},{"Terrain":1,"Triggers":[],"Character":null},{"Terrain":1,"Triggers":[],"Character":null},{"Terrain":1,"Triggers":[],"Character":null},{"Terrain":1,"Triggers":[],"Character":null},{"Terrain":1,"Triggers":[],"Character":null},{"Terrain":1,"Triggers":[],"Character":null},{"Terrain":1,"Triggers":[],"Character":null},{"Terrain":4,"Triggers":[],"Character":null},{"Terrain":4,"Triggers":[],"Character":null},{"Terrain":1,"Triggers":[],"Character":null},{"Terrain":1,"Triggers":[],"Character":null},{"Terrain":1,"Triggers":[],"Character":null},{"Terrain":1,"Triggers":[],"Character":null},{"Terrain":1,"Triggers":[],"Character":null},{"Terrain":1,"Triggers":[],"Character":null},{"Terrain":1,"Triggers":[],"Character":null},{"Terrain":1,"Triggers":[],"Character":null},{"Terrain":1,"Triggers":[],"Character":null},{"Terrain":1,"Triggers":[],"Character":null},{"Terrain":1,"Triggers":[],"Character":null},{"Terrain":1,"Triggers":[],"Character":null},{"Terrain":1,"Triggers":[],"Character":null},{"Terrain":1,"Triggers":[],"Character":null},{"Terrain":5,"Triggers":[],"Character":null},{"Terrain":5,"Triggers":[],"Character":null},{"Terrain":1,"Triggers":[],"Character":null},{"Terrain":1,"Triggers":[],"Character":null},{"Terrain":1,"Triggers":[],"Character":null},{"Terrain":1,"Triggers":[],"Character":null},{"Terrain":1,"Triggers":[],"Character":null},{"Terrain":1,"Triggers":[],"Character":null},{"Terrain":1,"Triggers":[],"Character":null},{"Terrain":1,"Triggers":[],"Character":null},{"Terrain":1,"Triggers":[],"Character":null},{"Terrain":1,"Triggers":[],"Character":null},{"Terrain":1,"Triggers":[],"Character":null},{"Terrain":1,"Triggers":[],"Character":null},{"Terrain":1,"Triggers":[],"Character":null},{"Terrain":1,"Triggers":[],"Character":null},{"Terrain":4,"Triggers":[],"Character":null},{"Terrain":4,"Triggers":[],"Character":null},{"Terrain":1,"Triggers":[],"Character":null},{"Terrain":1,"Triggers":[],"Character":null},{"Terrain":1,"Triggers":[],"Character":null},{"Terrain":1,"Triggers":[],"Character":null},{"Terrain":1,"Triggers":[],"Character":null},{"Terrain":1,"Triggers":[],"Character":null},{"Terrain":1,"Triggers":[],"Character":null},{"Terrain":1,"Triggers":[],"Character":null},{"Terrain":1,"Triggers":[],"Character":null},{"Terrain":1,"Triggers":[],"Character":null},{"Terrain":1,"Triggers":[],"Character":null},{"Terrain":1,"Triggers":[],"Character":null},{"Terrain":1,"Triggers":[],"Character":null},{"Terrain":1,"Triggers":[],"Character":null},{"Terrain":5,"Triggers":[],"Character":null},{"Terrain":5,"Triggers":[],"Character":null},{"Terrain":1,"Triggers":[],"Character":null},{"Terrain":1,"Triggers":[],"Character":null},{"Terrain":1,"Triggers":[],"Character":null},{"Terrain":1,"Triggers":[],"Character":null},{"Terrain":1,"Triggers":[],"Character":null},{"Terrain":1,"Triggers":[],"Character":null},{"Terrain":1,"Triggers":[],"Character":null},{"Terrain":1,"Triggers":[],"Character":null},{"Terrain":1,"Triggers":[],"Character":null},{"Terrain":1,"Triggers":[],"Character":null},{"Terrain":1,"Triggers":[],"Character":null},{"Terrain":1,"Triggers":[],"Character":null},{"Terrain":1,"Triggers":[],"Character":null},{"Terrain":1,"Triggers":[],"Character":null},{"Terrain":4,"Triggers":[],"Character":null},{"Terrain":4,"Triggers":[],"Character":null},{"Terrain":1,"Triggers":[],"Character":null},{"Terrain":1,"Triggers":[],"Character":null},{"Terrain":1,"Triggers":[],"Character":null},{"Terrain":1,"Triggers":[],"Character":null},{"Terrain":1,"Triggers":[],"Character":null},{"Terrain":1,"Triggers":[],"Character":null},{"Terrain":1,"Triggers":[],"Character":null},{"Terrain":1,"Triggers":[],"Character":null},{"Terrain":1,"Triggers":[],"Character":null},{"Terrain":1,"Triggers":[],"Character":null},{"Terrain":1,"Triggers":[],"Character":null},{"Terrain":1,"Triggers":[],"Character":null},{"Terrain":1,"Triggers":[],"Character":null},{"Terrain":1,"Triggers":[],"Character":null},{"Terrain":5,"Triggers":[],"Character":null},{"Terrain":5,"Triggers":[],"Character":null},{"Terrain":1,"Triggers":[],"Character":null},{"Terrain":1,"Triggers":[],"Character":null},{"Terrain":1,"Triggers":[],"Character":null},{"Terrain":1,"Triggers":[],"Character":null},{"Terrain":1,"Triggers":[],"Character":null},{"Terrain":1,"Triggers":[],"Character":null},{"Terrain":1,"Triggers":[],"Character":null},{"Terrain":1,"Triggers":[],"Character":null},{"Terrain":1,"Triggers":[],"Character":null},{"Terrain":1,"Triggers":[],"Character":null},{"Terrain":1,"Triggers":[],"Character":null},{"Terrain":1,"Triggers":[],"Character":null},{"Terrain":1,"Triggers":[],"Character":null},{"Terrain":1,"Triggers":[],"Character":null},{"Terrain":4,"Triggers":[],"Character":null},{"Terrain":4,"Triggers":[],"Character":null},{"Terrain":1,"Triggers":[],"Character":null},{"Terrain":1,"Triggers":[],"Character":null},{"Terrain":1,"Triggers":[],"Character":null},{"Terrain":1,"Triggers":[],"Character":null},{"Terrain":1,"Triggers":[],"Character":null},{"Terrain":1,"Triggers":[],"Character":null},{"Terrain":1,"Triggers":[],"Character":null},{"Terrain":1,"Triggers":[],"Character":null},{"Terrain":1,"Triggers":[],"Character":null},{"Terrain":1,"Triggers":[],"Character":null},{"Terrain":1,"Triggers":[],"Character":null},{"Terrain":1,"Triggers":[],"Character":null},{"Terrain":1,"Triggers":[],"Character":null},{"Terrain":1,"Triggers":[],"Character":null},{"Terrain":5,"Triggers":[],"Character":null},{"Terrain":5,"Triggers":[],"Character":null},{"Terrain":1,"Triggers":[],"Character":null},{"Terrain":1,"Triggers":[],"Character":null},{"Terrain":1,"Triggers":[],"Character":null},{"Terrain":1,"Triggers":[],"Character":null},{"Terrain":1,"Triggers":[],"Character":null},{"Terrain":1,"Triggers":[],"Character":null},{"Terrain":1,"Triggers":[],"Character":null},{"Terrain":1,"Triggers":[],"Character":null},{"Terrain":1,"Triggers":[],"Character":null},{"Terrain":1,"Triggers":[],"Character":null},{"Terrain":1,"Triggers":[],"Character":null},{"Terrain":1,"Triggers":[],"Character":null},{"Terrain":1,"Triggers":[],"Character":null},{"Terrain":1,"Triggers":[],"Character":null},{"Terrain":4,"Triggers":[],"Character":null},{"Terrain":4,"Triggers":[],"Character":null},{"Terrain":1,"Triggers":[],"Character":null},{"Terrain":1,"Triggers":[],"Character":null},{"Terrain":1,"Triggers":[],"Character":null},{"Terrain":1,"Triggers":[],"Character":null},{"Terrain":1,"Triggers":[],"Character":null},{"Terrain":1,"Triggers":[],"Character":null},{"Terrain":1,"Triggers":[],"Character":null},{"Terrain":1,"Triggers":[],"Character":null},{"Terrain":1,"Triggers":[],"Character":null},{"Terrain":1,"Triggers":[],"Character":null},{"Terrain":1,"Triggers":[],"Character":null},{"Terrain":1,"Triggers":[],"Character":null},{"Terrain":1,"Triggers":[],"Character":null},{"Terrain":1,"Triggers":[],"Character":null},{"Terrain":5,"Triggers":[],"Character":null},{"Terrain":5,"Triggers":[],"Character":null},{"Terrain":1,"Triggers":[],"Character":null},{"Terrain":1,"Triggers":[],"Character":null},{"Terrain":1,"Triggers":[],"Character":null},{"Terrain":1,"Triggers":[],"Character":null},{"Terrain":1,"Triggers":[],"Character":null},{"Terrain":1,"Triggers":[],"Character":null},{"Terrain":1,"Triggers":[],"Character":null},{"Terrain":1,"Triggers":[],"Character":null},{"Terrain":1,"Triggers":[],"Character":null},{"Terrain":1,"Triggers":[],"Character":null},{"Terrain":1,"Triggers":[],"Character":null},{"Terrain":1,"Triggers":[],"Character":null},{"Terrain":1,"Triggers":[],"Character":null},{"Terrain":1,"Triggers":[],"Character":null},{"Terrain":4,"Triggers":[],"Character":null},{"Terrain":4,"Triggers":[],"Character":null},{"Terrain":1,"Triggers":[],"Character":null},{"Terrain":1,"Triggers":[],"Character":null},{"Terrain":1,"Triggers":[],"Character":null},{"Terrain":1,"Triggers":[],"Character":null},{"Terrain":1,"Triggers":[],"Character":null},{"Terrain":1,"Triggers":[],"Character":null},{"Terrain":1,"Triggers":[],"Character":null},{"Terrain":1,"Triggers":[],"Character":null},{"Terrain":1,"Triggers":[],"Character":null},{"Terrain":1,"Triggers":[],"Character":null},{"Terrain":1,"Triggers":[],"Character":null},{"Terrain":1,"Triggers":[],"Character":null},{"Terrain":1,"Triggers":[],"Character":null},{"Terrain":1,"Triggers":[],"Character":null},{"Terrain":5,"Triggers":[],"Character":null},{"Terrain":5,"Triggers":[],"Character":null},{"Terrain":1,"Triggers":[],"Character":null},{"Terrain":1,"Triggers":[],"Character":null},{"Terrain":1,"Triggers":[],"Character":null},{"Terrain":1,"Triggers":[],"Character":null},{"Terrain":1,"Triggers":[],"Character":null},{"Terrain":1,"Triggers":[],"Character":null},{"Terrain":1,"Triggers":[],"Character":null},{"Terrain":1,"Triggers":[],"Character":null},{"Terrain":1,"Triggers":[],"Character":null},{"Terrain":1,"Triggers":[],"Character":null},{"Terrain":1,"Triggers":[],"Character":null},{"Terrain":1,"Triggers":[],"Character":null},{"Terrain":1,"Triggers":[],"Character":null},{"Terrain":1,"Triggers":[],"Character":null},{"Terrain":4,"Triggers":[],"Character":null},{"Terrain":2,"Triggers":[],"Character":null},{"Terrain":3,"Triggers":[],"Character":null},{"Terrain":3,"Triggers":[],"Character":null},{"Terrain":3,"Triggers":[],"Character":null},{"Terrain":3,"Triggers":[],"Character":null},{"Terrain":3,"Triggers":[],"Character":null},{"Terrain":3,"Triggers":[],"Character":null},{"Terrain":3,"Triggers":[],"Character":null},{"Terrain":3,"Triggers":[],"Character":null},{"Terrain":3,"Triggers":[],"Character":null},{"Terrain":3,"Triggers":[],"Character":null},{"Terrain":3,"Triggers":[],"Character":null},{"Terrain":3,"Triggers":[],"Character":null},{"Terrain":3,"Triggers":[],"Character":null},{"Terrain":2,"Triggers":[],"Character":null},{"Terrain":5,"Triggers":[{"TriggerType":0,"Teleport":{"DestinationMap":"Overworld","DestinationX":10,"DestinationY":11},"Shoppe":null}],"Character":null},{"Terrain":5,"Triggers":[{"TriggerType":0,"Teleport":{"DestinationMap":"Overworld","DestinationX":10,"DestinationY":11},"Shoppe":null}],"Character":null},{"Terrain":2,"Triggers":[],"Character":null},{"Terrain":3,"Triggers":[],"Character":null},{"Terrain":3,"Triggers":[],"Character":null},{"Terrain":3,"Triggers":[],"Character":null},{"Terrain":3,"Triggers":[],"Character":null},{"Terrain":3,"Triggers":[],"Character":null},{"Terrain":3,"Triggers":[],"Character":null},{"Terrain":3,"Triggers":[],"Character":null},{"Terrain":3,"Triggers":[],"Character":null},{"Terrain":3,"Triggers":[],"Character":null},{"Terrain":3,"Triggers":[],"Character":null},{"Terrain":3,"Triggers":[],"Character":null},{"Terrain":3,"Triggers":[],"Character":null},{"Terrain":3,"Triggers":[],"Character":null},{"Terrain":2,"Triggers":[],"Character":null}],"DefaultTerrain":1}